multiplexer/mux81/mux81_bh.v
`timescale 1ns / 1ps
module mux81_bh(
  input  logic i0, i1, i2, i3, i4, i5, i6, i7,
  input  logic [2:0] s,
  output logic y
);

  // Behavioral modeling using if-else chain
  always_comb begin
    if (s == 3'b000)
      y = i0;
    else if (s == 3'b001)
      y = i1;
    else if (s == 3'b010)
      y = i2;
    else if (s == 3'b011)
      y = i3;
    else if (s == 3'b100)
      y = i4;
    else if (s == 3'b101)
      y = i5;
    else if (s == 3'b110)
      y = i6;
    else
      y = i7;
  end

endmodule

multiplexer/mux81/mux81_tb.v
`timescale 1ns / 1ps
module mux81_tb;

  logic i0, i1, i2, i3, i4, i5, i6, i7;
  logic [2:0] s;
  logic y;

  // Instantiate one of the models
  // mux81_df dut (.*);
  // mux81_st dut (.*);
  mux81_bh dut (.*);

initial begin
  $dumpfile("mux81_tb.vcd");
  $dumpvars(0, mux81_tb);
  $monitor("Time=%0t | s=%b | y=%b", $time, s, y);

  // Set inputs to distinct values
  i0=0; i1=1; i2=0; i3=1; i4=0; i5=1; i6=0; i7=1;

  // Cycle through all select values
  for (int k = 0; k < 8; k++) begin
    s = k;
    #10;
  end

  $finish;
end

endmodule

multiplexer/mux81/mux81_tb.vcd
$date
	Tue Oct 07 23:28:25 2025
$end
$version
	Icarus Verilog
$end
$timescale
	1ps
$end
$scope module mux81_tb $end
$var wire 1 ! y $end
$var reg 1 " i0 $end
$var reg 1 # i1 $end
$var reg 1 $ i2 $end
$var reg 1 % i3 $end
$var reg 1 & i4 $end
$var reg 1 ' i5 $end
$var reg 1 ( i6 $end
$var reg 1 ) i7 $end
$var reg 3 * s [2:0] $end
$scope module dut $end
$var wire 1 " i0 $end
$var wire 1 # i1 $end
$var wire 1 $ i2 $end
$var wire 1 % i3 $end
$var wire 1 & i4 $end
$var wire 1 ' i5 $end
$var wire 1 ( i6 $end
$var wire 1 ) i7 $end
$var wire 3 + s [2:0] $end
$var reg 1 ! y $end
$upscope $end
$scope begin $ivl_for_loop0 $end
$var integer 32 , k [31:0] $end
$upscope $end
$upscope $end
$enddefinitions $end
$comment Show the parameter values. $end
$dumpall
$end
#0
$dumpvars
b0 ,
b0 +
b0 *
1)
0(
1'
0&
1%
0$
1#
0"
0!
$end
#10000
1!
b1 *
b1 +
b1 ,
#20000
0!
b10 *
b10 +
b10 ,
#30000
1!
b11 *
b11 +
b11 ,
#40000
0!
b100 *
b100 +
b100 ,
#50000
1!
b101 *
b101 +
b101 ,
#60000
0!
b110 *
b110 +
b110 ,
#70000
1!
b111 *
b111 +
b111 ,
#80000
b1000 ,
