adder/full adder/full_adder_st.v
// Half Adder module
module half_adder (
    input  logic a, b,
    output logic sum, carry
);
    assign sum   = a ^ b;
    assign carry = a & b;
endmodule

// Full Adder Structural
module full_adder_st (
    input  logic a, b, cin,
    output logic sum, cout
);
    logic sum1, carry1, carry2;

    // First half adder
    half_adder ha1(.a(a), .b(b), .sum(sum1), .carry(carry1));

    // Second half adder
    half_adder ha2(.a(sum1), .b(cin), .sum(sum), .carry(carry2));

    // OR gate for final carry
    assign cout = carry1 | carry2;
endmodule

adder/full adder/full_adder_bh.v
module full_adder_bh (
    input  logic a, b, cin,
    output logic sum, cout
);
    always_comb begin
        {cout, sum} = a + b + cin;  
    end
endmodule

adder/full adder/full_adder_df.v
module full_adder_df (
    input  logic a, b, cin,
    output logic sum, cout
);
    // Dataflow: use continuous assignments with logic expressions
    assign sum  = a ^ b ^ cin;
    assign cout = (a & b) | (b & cin) | (a & cin);
endmodule

adder/full adder/full_adder_tb.v
`timescale 1ns/1ps
module full_adder_tb;
    logic a, b, cin;
    logic sum_df, cout_df;
    logic sum_bh, cout_bh;
    logic sum_st, cout_st;

    // Instantiate each version
    full_adder_df df(.a(a), .b(b), .cin(cin), .sum(sum_df), .cout(cout_df));
    full_adder_bh bh(.a(a), .b(b), .cin(cin), .sum(sum_bh), .cout(cout_bh));
    full_adder_st st(.a(a), .b(b), .cin(cin), .sum(sum_st), .cout(cout_st));

    initial begin
        $dumpfile("full_adder_tb.vcd");
        $dumpvars(0, full_adder_tb);
        $display("Testing Full Adder: Dataflow || Behavioral || Structural");
        $display("Time  | a b cin | sum_df cout_df | sum_bh cout_bh | sum_st cout_st");

        // Apply all 8 combinations
        for (int i = 0; i < 8; i++) begin
            {a, b, cin} = i;
            #10;
            $display("%4t | %b %b  %b  |   %b      %b    |   %b      %b    |   %b      %b",
                     $time, a, b, cin,
                     sum_df, cout_df,
                     sum_bh, cout_bh,
                     sum_st, cout_st);
        end

        $finish;
    end
endmodule

adder/full adder/full_adder_tb.vcd
$date
	Tue Sep 23 19:45:24 2025
$end
$version
	Icarus Verilog
$end
$timescale
	1ps
$end
$scope module full_adder_tb $end
$var wire 1 ! sum_st $end
$var wire 1 " sum_df $end
$var wire 1 # sum_bh $end
$var wire 1 $ cout_st $end
$var wire 1 % cout_df $end
$var wire 1 & cout_bh $end
$var reg 1 ' a $end
$var reg 1 ( b $end
$var reg 1 ) cin $end
$scope module bh $end
$var wire 1 ' a $end
$var wire 1 ( b $end
$var wire 1 ) cin $end
$var reg 1 & cout $end
$var reg 1 # sum $end
$upscope $end
$scope module df $end
$var wire 1 ' a $end
$var wire 1 ( b $end
$var wire 1 ) cin $end
$var wire 1 % cout $end
$var wire 1 " sum $end
$upscope $end
$scope module st $end
$var wire 1 ' a $end
$var wire 1 ( b $end
$var wire 1 ) cin $end
$var wire 1 $ cout $end
$var wire 1 * sum1 $end
$var wire 1 ! sum $end
$var wire 1 + carry2 $end
$var wire 1 , carry1 $end
$scope module ha1 $end
$var wire 1 ' a $end
$var wire 1 ( b $end
$var wire 1 , carry $end
$var wire 1 * sum $end
$upscope $end
$scope module ha2 $end
$var wire 1 * a $end
$var wire 1 ) b $end
$var wire 1 + carry $end
$var wire 1 ! sum $end
$upscope $end
$upscope $end
$scope begin $ivl_for_loop0 $end
$var integer 32 - i [31:0] $end
$upscope $end
$upscope $end
$enddefinitions $end
$comment Show the parameter values. $end
$dumpall
$end
#0
$dumpvars
b0 -
0,
0+
0*
0)
0(
0'
0&
0%
0$
0#
0"
0!
$end
#10000
1#
1"
1!
1)
b1 -
#20000
1*
1"
1!
1(
0)
b10 -
#30000
1%
1$
1&
0#
0"
0!
1+
1)
b11 -
#40000
0%
0$
0&
1#
1"
1!
0+
1'
0(
0)
b100 -
#50000
1%
1$
1&
0#
0"
0!
1+
1)
b101 -
#60000
1%
0*
1,
0"
0!
0+
1(
0)
b110 -
#70000
1#
1"
1!
1)
b111 -
#80000
b1000 -
