subtractor/full subtractor/full_sub_st.v
// Half subtractor used in structural model
module half_sub (
    input  logic a, b,
    output logic diff, borrow
);
    assign diff   = a ^ b;
    assign borrow = ~a & b;
endmodule

// Full subtractor built using two half subtractors
module full_sub_st (
    input  logic a, b, bin,
    output logic diff, bout
);
    logic d1, b1, d2, b2;

    half_sub hs1 (.a(a), .b(b),   .diff(d1), .borrow(b1));
    half_sub hs2 (.a(d1), .b(bin), .diff(d2), .borrow(b2));

    assign diff = d2;
    assign bout = b1 | b2;
endmodule

subtractor/full subtractor/full_sub_bh.v
module full_sub_bh (
    input  logic a, b, bin,
    output logic diff, bout
);
    always_comb begin
        diff = a ^ b ^ bin;
        bout = (~a & b) | (~(a ^ b) & bin);
    end
endmodule

subtractor/full subtractor/full_sub_df.v
module full_sub_df (
    input  logic a, b, bin,
    output logic diff, bout
);
    assign diff = a ^ b ^ bin;
    assign bout = (~a & b) | (~(a ^ b) & bin);
endmodule

subtractor/full subtractor/full_sub_tb.v
`timescale 1ns / 1ps
module full_sub_tb;
    logic a, b, bin;
    logic diff_df, bout_df;
    logic diff_bh, bout_bh;
    logic diff_st, bout_st;
    integer i;

    // Instantiate all models
    full_sub_df u1 (.a(a), .b(b), .bin(bin), .diff(diff_df), .bout(bout_df));
    full_sub_bh u2 (.a(a), .b(b), .bin(bin), .diff(diff_bh), .bout(bout_bh));
    full_sub_st u3 (.a(a), .b(b), .bin(bin), .diff(diff_st), .bout(bout_st));

    initial begin
        $dumpfile("full_sub_tb.vcd");
        $dumpvars(0, full_sub_tb);
        $display("Testing Full Subtractor");

        $monitor("t=%0t | a=%b b=%b bin=%b | DF: diff=%b bout=%b | BH: diff=%b bout=%b | ST: diff=%b bout=%b",
                 $time, a, b, bin,
                 diff_df, bout_df, diff_bh, bout_bh, diff_st, bout_st);

        for (i = 0; i < 8; i++) begin
            {a, b, bin} = i;
            #10;
        end
        $finish;
    end
endmodule

subtractor/full subtractor/full_sub_tb.vcd
$date
	Tue Sep 23 22:09:37 2025
$end
$version
	Icarus Verilog
$end
$timescale
	1ps
$end
$scope module full_sub_tb $end
$var wire 1 ! diff_st $end
$var wire 1 " diff_df $end
$var wire 1 # diff_bh $end
$var wire 1 $ bout_st $end
$var wire 1 % bout_df $end
$var wire 1 & bout_bh $end
$var reg 1 ' a $end
$var reg 1 ( b $end
$var reg 1 ) bin $end
$var integer 32 * i [31:0] $end
$scope module u1 $end
$var wire 1 ' a $end
$var wire 1 ( b $end
$var wire 1 ) bin $end
$var wire 1 % bout $end
$var wire 1 " diff $end
$upscope $end
$scope module u2 $end
$var wire 1 ' a $end
$var wire 1 ( b $end
$var wire 1 ) bin $end
$var reg 1 & bout $end
$var reg 1 # diff $end
$upscope $end
$scope module u3 $end
$var wire 1 ' a $end
$var wire 1 ( b $end
$var wire 1 ) bin $end
$var wire 1 $ bout $end
$var wire 1 ! diff $end
$var wire 1 + d2 $end
$var wire 1 , d1 $end
$var wire 1 - b2 $end
$var wire 1 . b1 $end
$scope module hs1 $end
$var wire 1 ' a $end
$var wire 1 ( b $end
$var wire 1 . borrow $end
$var wire 1 , diff $end
$upscope $end
$scope module hs2 $end
$var wire 1 , a $end
$var wire 1 ) b $end
$var wire 1 - borrow $end
$var wire 1 + diff $end
$upscope $end
$upscope $end
$upscope $end
$enddefinitions $end
$comment Show the parameter values. $end
$dumpall
$end
#0
$dumpvars
0.
0-
0,
0+
b0 *
0)
0(
0'
0&
0%
0$
0#
0"
0!
$end
#10000
1%
1$
1"
1&
1#
1!
1+
1-
1)
b1 *
#20000
1,
1.
1"
1!
1+
0-
1(
0)
b10 *
#30000
0"
0#
0!
0+
1)
b11 *
#40000
0%
0$
0.
1"
0&
1#
1!
1+
1'
0(
0)
b100 *
#50000
0"
0#
0!
0+
1)
b101 *
#60000
0,
0"
0!
0+
1(
0)
b110 *
#70000
1%
1$
1"
1&
1#
1!
1+
1-
1)
b111 *
#80000
b1000 *
