multiplexer/mux21/mux21_df.v
module mux21_df(
input logic i0, i1, s,
output logic y
);
assign y = (i0 & (~s)) | (i1 & s);
endmodule

multiplexer/mux21/mux21_tb.v
`timescale 1ns / 1ps
module mux21_tb;

  logic i0, i1, s;
  logic y;

  // Instantiate DUT with wildcard connection
  mux21_df dut (.*);

  initial begin
    // Create VCD file for waveform
    $dumpfile("mux21_tb.vcd");
    $dumpvars(0, mux21_tb);

    // Monitor signal changes
    $monitor("Time=%0t | i0=%b i1=%b s=%b | y=%b", $time, i0, i1, s, y);

    // Test all input combinations
    for (int i = 0; i < 8; i++) begin
      {s, i1, i0} = i;  // Correct bit order: select first
      #10;
    end

    $finish;
  end
endmodule

multiplexer/mux21/mux21_tb.vcd
$date
	Tue Oct 07 22:55:58 2025
$end
$version
	Icarus Verilog
$end
$timescale
	1ps
$end
$scope module mux21_tb $end
$var wire 1 ! y $end
$var reg 1 " i0 $end
$var reg 1 # i1 $end
$var reg 1 $ s $end
$scope module dut $end
$var wire 1 " i0 $end
$var wire 1 # i1 $end
$var wire 1 $ s $end
$var wire 1 ! y $end
$upscope $end
$scope begin $ivl_for_loop0 $end
$var integer 32 % i [31:0] $end
$upscope $end
$upscope $end
$enddefinitions $end
$comment Show the parameter values. $end
$dumpall
$end
#0
$dumpvars
b0 %
0$
0#
0"
0!
$end
#10000
1!
1"
b1 %
#20000
0!
1#
0"
b10 %
#30000
1!
1"
b11 %
#40000
0!
1$
0#
0"
b100 %
#50000
1"
b101 %
#60000
1!
1#
0"
b110 %
#70000
1"
b111 %
#80000
b1000 %
